git_hotspot_ai/__init__.py
git_hotspot_ai/__main__.py
git_hotspot_ai/cli.py
git_hotspot_ai/core.py
git_hotspot_ai-0.8.0.dist-info/licenses/LICENSE
git_hotspot_ai-0.8.0.dist-info/METADATA
git_hotspot_ai-0.8.0.dist-info/WHEEL
git_hotspot_ai-0.8.0.dist-info/entry_points.txt
git_hotspot_ai-0.8.0.dist-info/top_level.txt
git_hotspot_ai-0.8.0.dist-info/RECORD
